LICENSE.md
MANIFEST.in
README.md
setup.py
GWAS_benchmark/__init__.py
GWAS_benchmark/cluster_data.py
GWAS_benchmark/methods.py
GWAS_benchmark/semisynth_simulations.py
GWAS_benchmark/snp_gen.py
GWAS_benchmark/split_data_helper.py
GWAS_benchmark.egg-info/PKG-INFO
GWAS_benchmark.egg-info/SOURCES.txt
GWAS_benchmark.egg-info/dependency_links.txt
GWAS_benchmark.egg-info/requires.txt
GWAS_benchmark.egg-info/top_level.txt
GWAS_benchmark/tests/__init__.py
GWAS_benchmark/tests/test_semisynth.py
GWAS_benchmark/tests/test_snp_gen.py
GWAS_benchmark/tests/__init__.py
GWAS_benchmark/tests/test_semisynth.py
GWAS_benchmark/tests/test_snp_gen.py