Metadata-Version: 1.0
Name: GWAS-benchmark
Version: 0.1.1
Summary: GWAS benchmark
Home-page: http://research.microsoft.com/en-us/um/redmond/projects/mscompbio/
Author: MSR
Author-email: fastlmm@microsoft.com
License: Apache 2.0
Keywords: gwas bioinformatics benchmarks
Platform: UNKNOWN
